fenic_cloud/__init__.py
fenic_cloud/auth_client/__init__.py
fenic_cloud/auth_client/client.py
fenic_cloud/hasura_client/__init__.py
fenic_cloud/hasura_client/client.py
fenic_cloud/hasura_client/hasura_execution.py
fenic_cloud/hasura_client/custom_base_client/async_base_client.py
fenic_cloud/hasura_client/generated_graphql_client/__init__.py
fenic_cloud/hasura_client/generated_graphql_client/add_s_3_bucket_access_configurations.py
fenic_cloud/hasura_client/generated_graphql_client/add_s_3_operation_permissions.py
fenic_cloud/hasura_client/generated_graphql_client/async_base_client.py
fenic_cloud/hasura_client/generated_graphql_client/base_model.py
fenic_cloud/hasura_client/generated_graphql_client/client.py
fenic_cloud/hasura_client/generated_graphql_client/create_app.py
fenic_cloud/hasura_client/generated_graphql_client/create_ephemeral_catalog.py
fenic_cloud/hasura_client/generated_graphql_client/create_execution_session_for_app.py
fenic_cloud/hasura_client/generated_graphql_client/create_external_id_reservation.py
fenic_cloud/hasura_client/generated_graphql_client/create_namespace.py
fenic_cloud/hasura_client/generated_graphql_client/create_namespace_with_properties.py
fenic_cloud/hasura_client/generated_graphql_client/create_query_execution.py
fenic_cloud/hasura_client/generated_graphql_client/create_query_execution_metric.py
fenic_cloud/hasura_client/generated_graphql_client/create_s_3_access_role.py
fenic_cloud/hasura_client/generated_graphql_client/create_s_3_bucket_access_configurations.py
fenic_cloud/hasura_client/generated_graphql_client/create_s_3_bucket_operation_permissions.py
fenic_cloud/hasura_client/generated_graphql_client/create_standard_catalog.py
fenic_cloud/hasura_client/generated_graphql_client/create_table.py
fenic_cloud/hasura_client/generated_graphql_client/create_table_with_properties.py
fenic_cloud/hasura_client/generated_graphql_client/create_user.py
fenic_cloud/hasura_client/generated_graphql_client/create_view.py
fenic_cloud-0.1.3.dist-info/METADATA
fenic_cloud-0.1.3.dist-info/WHEEL
fenic_cloud-0.1.3.dist-info/licenses/LICENSE
fenic_cloud-0.1.3.dist-info/RECORD
